Workbook
Name CENTROGESTOR: #REF!
Name CENTROGESTORDEPENDENCIA: #REF!
Name DEPENDENCIA: #REF!
Name FONDO: #REF!
Name FONDOS: [1]MYLIST!$C$2:$C$126
Name FUT: #REF!
Name k: '[2]LISTA MPD'!$C$2:$C$18
Name METAAFPDCC: #REF!
Name METAPDCC: #REF!
Name METASAFPDCC: #REF!
Name METASAFPDM: #REF!
Name METASPDCC: #REF!
Name METASPDM: '[3]LISTA MPD'!$A$2:$A$616
Name POSPRE: #REF!

Sheet Ppto General
B1: PRESUPUESTO DETALLADO DEL PROYECTO DE INVERSIÓN | K1: Código: FO-M1-P1-24
K2: Versión: 02
K3: Fecha de aprobación: 13/06/2025
K4: Página 1 de 1
A6: NOMBRE DEL PROYECTO: | L6: TIPO DE MODIFICACIÓN | M6: VALOR DE LA MODIFICACIÓN
A7: ENTIDAD / DEPENDENCIA
A8: VIGENCIA | D8: CÓDIGO PI: | H8: ID MGA O CÓDIGO BPIN:
A10: CADENA DE VALOR PROYECTO | F10: CCPT-CLASIFICACION CENTRAL PRODUCTO - DANE (CUENTA GASTO) | H10: PRESUPUESTO | L10: RECURSOS POR GESTIONAR / ASIGNAR | M10: VALOR TOTAL DEL PROYECTO
A11: OBJETIVOS ESPECÍFICOS | B11: PRODUCTO MGA | C11: ENTREGABLE EN MGA (APLICA SOLO PARA PROYECTOS CON EDT) | D11: ACTIVIDAD DEL PROYECTO | E11: FUENTE DE FINANCIACIÓN | F11: CÓDIGO | G11: NOMBRE CUENTA | H11: UNIDAD DE MEDIDA | I11: CANTIDAD | J11: VALOR DE LA ACTIVIDAD APROPIADOS (DEPTO O PROPIOS DE DESCENTRALIZADA) | K11: VALOR DE LA ACTIVIDAD (APLICA PARA RECURSOS NACIÓN)
C26: Subtotal Proyecto | K26: =SUM(K12:K25) -> 0 | L26: =SUM(L12:L25) -> 0 | M26: =SUM(M12:M25) -> 0
A28: NOTA: Para tener la trazabilidad de modificaciones, es importante y obligatorio que diligencien la pestaña "Historico de Modificaciones" y sea cargado este archivo en SAP, dentro de la carpeta "Presupuesto"
A34: Datos del Formulador
A35: Nombre Completo:
A36: Cargo:
A37: Firma del formulador:
A38: Fecha:
A40: VoBo Director, Secretario de Despacho o Gerente de la Entidad
A43: CONTROL DE CAMBIOS
A44: Versión | B44: Descripción del Cambio | E44: Fecha
A45: 1 | B45: Corresponde a la creación del Documento | E45: 45259
A46: 2 | B46: Se agregó la columna“Recursos de Entidad Descentralizada” se ajustó la redacción de las columnas J, K y L para mayor claridad, en atención a las observaciones realizadas por el equipo de la Subdirección de Inversión Pública durante las mesas de trabajo sobre revisión de formatos, Procedimientos y adecuación a la nueva Plataforma Integrada de Inversión Pública (PIIP). | E46: 45821
A49: Elaboró | F49: Revisó | K49: Aprobó
A50: Nombres: Profesionales Subdirección de Inversión Pública | F50: Nombre: Diego Felipe Bustamante A., Lina María Sarria Duarte, Yolanda Urbano Rodriguez | K50: Mesa de Trabajo con el proceso M1-P3 Administración del MIPG Acta No. 020 del 13/06/2025
A51: Cargo: Profesional Universitario y especializado | F51: Cargo: Subdirector Ordenamiento y Desarrollo Regional Subdirectora de Inversión Pública Líder Profesional Especializada Líder del Proceso
A52: Firma: | F52: Firma:
A53: Fecha: : 15/05/2025 | F53: Fecha: 15/05/2025 | K53: Fecha: 13/06/2025

Sheet Historico de Modificaciones
B1: PRESUPUESTO DETALLADO DEL PROYECTO DE INVERSIÓN | K1: Código: FO-M1-P1-24
K2: Versión: 02
K3: Fecha de aprobación: 13/06/2025
K4: Página 1 de 1
A6: NOMBRE DEL PROYECTO: | B6: =+'Ppto General'!B6:K6 -> 0 | L6: TIPO DE MODIFICACIÓN | M6: VALOR DE LA MODIFICACIÓN
A7: ENTIDAD / DEPENDENCIA | B7: =+'Ppto General'!B7:K7 -> 0 | L7: =+'Ppto General'!L7:L8 -> 0 | M7: =+'Ppto General'!M7:M8 -> 0
A8: VIGENCIA | B8: =+'Ppto General'!B8:C8 -> 0 | D8: CÓDIGO PI: | G8: CÓDIGO BPIN:
A10: ACTVIDAD | B10: FUENTE DE FINANCIACIÓN | C10: PRESUPUESTO INICIAL | D10: MODIFICACIÓN 1 | E10: MODIFICACIÓN 2 | F10: MODIFICACIÓN 3 | G10: MODIFICACIÓN 4 | H10: MODIFICACIÓN 5 | I10: MODIFICACIÓN 6 | J10: MODIFICACIÓN 7 | K10: MODIFICACIÓN 8 | L10: RECURSOS DE GESTIÓN | M10: VALOR TOTALDEL PROYECTO
D11: (DD-MM) | E11: (DD-MM) | F11: (DD-MM) | G11: (DD-MM) | H11: (DD-MM) | I11: (DD-MM) | J11: (DD-MM) | K11: (DD-MM)
M12: =+L12+K12 -> 0
M13: =+L13+K13 -> 0
M14: =+L14+K14 -> 0
M15: =+L15+K15 -> 0
M16: =+L16+K16 -> 0
M17: =+L17+K17 -> 0
M18: =+L18+K18 -> 0
M19: =+L19+K19 -> 0
M20: =+L20+K20 -> 0
M21: =+L21+K21 -> 0
M22: =+L22+K22 -> 0
M23: =+L23+K23 -> 0
... M25: =+L25+K25 -> 0
A26: Subtotal Proyecto | C26: =SUM(C12:C25) -> 0 | D26: =SUM(D12:D25) -> 0 | E26: =SUM(E12:E25) -> 0 | F26: =SUM(F12:F25) -> 0 | G26: =SUM(G12:G25) -> 0 | H26: =SUM(H12:H25) -> 0 | I26: =SUM(I12:I25) -> 0 | J26: =SUM(J12:J25) -> 0 | ... M26: =SUM(M12:M25) -> 0
A28: Elaboró | F28: Revisó | K28: Aprobó
A29: Nombres: Profesionales Subdirección de Inversión Pública | F29: Nombre: Diego Felipe Bustamante A., Lina María Sarria Duarte, Yolanda Urbano Rodriguez | K29: Mesa de Trabajo con el proceso M1-P3 Administración del MIPG Acta No. 020 del 13/06/2025
A30: Cargo: Profesional Universitario y especializado | F30: Cargo: Subdirector Ordenamiento y Desarrollo Regional Subdirectora de Inversión Pública Líder Profesional Especializada Líder del Proceso
A31: Firma: | F31: Firma:
A32: Fecha: 15/05/2025 | F32: Fecha: 15/05/2025 | K32: Fecha: 13/06/2025
